rivet/__init__.py
rivet/__init__.pyi
rivet/__pycache__/__init__.cpython-312.pyc
rivet/__pycache__/__init__.cpython-313.pyc
rivet/rivet.cpython-313t-aarch64-linux-gnu.so
rivet_rs-0.1.2.dist-info/METADATA
rivet_rs-0.1.2.dist-info/WHEEL
rivet_rs-0.1.2.dist-info/licenses/LICENSE
rivet_rs-0.1.2.dist-info/RECORD
