Metadata-Version: 2.4
Name: rivet-rs
Version: 0.1.2
Classifier: Development Status :: 3 - Alpha
Classifier: Intended Audience :: Science/Research
Classifier: License :: OSI Approved :: MIT License
Classifier: Programming Language :: Python :: 3
Classifier: Programming Language :: Python :: 3.9
Classifier: Programming Language :: Python :: 3.10
Classifier: Programming Language :: Python :: 3.11
Classifier: Programming Language :: Python :: 3.12
Classifier: Programming Language :: Rust
Classifier: Topic :: Scientific/Engineering :: Bio-Informatics
Requires-Dist: numpy>=1.24
Requires-Dist: pytest>=7.0 ; extra == 'dev'
Provides-Extra: dev
License-File: LICENSE
Summary: Rivet - Structural Alignment of Multiple Proteins
Keywords: bioinformatics,protein,structure,alignment,rivet
Author: msinclair
License-Expression: MIT
Requires-Python: >=3.9
Project-URL: Documentation, https://github.com/msinclair/rivet
Project-URL: Homepage, https://github.com/msinclair/rivet
Project-URL: Repository, https://github.com/msinclair/rivet
